portablemc_quilt/__init__.py
portablemc_quilt-1.0.1.dist-info/WHEEL
portablemc_quilt-1.0.1.dist-info/METADATA
portablemc_quilt-1.0.1.dist-info/RECORD
