Metadata-Version: 2.1
Name: portablemc-quilt
Version: 1.0.1
Summary: Start Minecraft using the Quilt mod loader using '<exec> start quilt:[<mc-version>[:<loader-version>]]'.
License: GPL-3.0-only
Author: MisileLaboratory
Requires-Python: >=3.6
Classifier: License :: OSI Approved :: GNU General Public License v3 (GPLv3)
Classifier: Programming Language :: Python :: 3
Classifier: Programming Language :: Python :: 3.6
Classifier: Programming Language :: Python :: 3.7
Classifier: Programming Language :: Python :: 3.8
Classifier: Programming Language :: Python :: 3.9
Classifier: Programming Language :: Python :: 3.10
Requires-Dist: portablemc (>=3,<4)
